setup.py
django_parting.egg-info/PKG-INFO
django_parting.egg-info/SOURCES.txt
django_parting.egg-info/dependency_links.txt
django_parting.egg-info/namespace_packages.txt
django_parting.egg-info/not-zip-safe
django_parting.egg-info/requires.txt
django_parting.egg-info/top_level.txt
parting/__init__.py
parting/models.py
parting/tests.py
parting/management/__init__.py
parting/management/commands/__init__.py
parting/management/commands/ensure_partition.py