Metadata-Version: 1.1
Name: django-parting
Version: 0.0.2
Summary: Tools to help manage large database tables
Home-page: https://github.com/danfairs/django-parting
Author: Dan Fairs
Author-email: dan@fezconsulting.com
License: BSD
Keywords: django partition database table
Platform: UNKNOWN
Classifier: Programming Language :: Python
Classifier: Topic :: Software Development :: Libraries :: Python Modules
Classifier: Framework :: Django
Classifier: Development Status :: 3 - Alpha
Classifier: License :: OSI Approved :: BSD License
